stat_prob_distributions/Binomialdistribution.py
stat_prob_distributions/Gaussiandistribution.py
stat_prob_distributions/Generaldistribution.py
stat_prob_distributions/__init__.py
stat_prob_distributions-0.1.dist-info/DESCRIPTION.rst
stat_prob_distributions-0.1.dist-info/METADATA
stat_prob_distributions-0.1.dist-info/RECORD
stat_prob_distributions-0.1.dist-info/WHEEL
stat_prob_distributions-0.1.dist-info/metadata.json
stat_prob_distributions-0.1.dist-info/top_level.txt
