Metadata-Version: 2.0
Name: stat-prob-distributions
Version: 0.1
Summary: Gaussian  and Binomial distributions
Home-page: UNKNOWN
Author: UNKNOWN
Author-email: UNKNOWN
License: UNKNOWN
Platform: UNKNOWN
